langchain_modelverse/__init__.py
langchain_modelverse-0.0.1.dist-info/METADATA
langchain_modelverse-0.0.1.dist-info/WHEEL
langchain_modelverse-0.0.1.dist-info/top_level.txt
langchain_modelverse-0.0.1.dist-info/RECORD
