Metadata-Version: 2.1
Name: langchain-modelverse
Version: 0.0.1
Summary: LangChain Custom LLM for ModelVerse
Author: John Doe
Author-email: johndoe@johndoe.com
Keywords: python
Requires-Dist: langchain
Requires-Dist: requests
